escape_path.py
escape_path-0.1.0.dist-info/licenses/LICENSE
escape_path-0.1.0.dist-info/METADATA
escape_path-0.1.0.dist-info/WHEEL
escape_path-0.1.0.dist-info/top_level.txt
escape_path-0.1.0.dist-info/RECORD
