Metadata-Version: 2.4
Name: escape-path
Version: 0.1.0
Summary: A lightweight Python utility to safely escape file paths for command-line usage.
Author-email: Jifeng Wu <jifengwu2k@gmail.com>
License-Expression: MIT
Project-URL: Homepage, https://github.com/jifengwu2k/escape-path
Project-URL: Bug Tracker, https://github.com/jifengwu2k/escape-path/issues
Classifier: Programming Language :: Python :: 3
Classifier: Operating System :: OS Independent
Requires-Python: >=3
License-File: LICENSE
Dynamic: license-file
